mmagic/__init__.py
mmagic/registry.py
mmagic/version.py
mmagic/.mim/model-index.yml
mmagic/.mim/configs/_base_/default_runtime.py
mmagic/.mim/configs/_base_/gen_default_runtime.py
mmagic/.mim/configs/_base_/inpaint_default_runtime.py
mmagic/.mim/configs/_base_/matting_default_runtime.py
mmagic/.mim/configs/_base_/datasets/basicvsr_test_config.py
mmagic/.mim/configs/_base_/datasets/celeba.py
mmagic/.mim/configs/_base_/datasets/cifar10_noaug.py
mmagic/.mim/configs/_base_/datasets/cifar10_nopad.py
mmagic/.mim/configs/_base_/datasets/comp1k.py
mmagic/.mim/configs/_base_/datasets/deblurring-defocus_test_config.py
mmagic/.mim/configs/_base_/datasets/deblurring-motion_test_config.py
mmagic/.mim/configs/_base_/datasets/decompression_test_config.py
mmagic/.mim/configs/_base_/datasets/denoising-gaussian_color_test_config.py
mmagic/.mim/configs/_base_/datasets/denoising-gaussian_gray_test_config.py
mmagic/.mim/configs/_base_/datasets/denoising-real_test_config.py
mmagic/.mim/configs/_base_/datasets/deraining_test_config.py
mmagic/.mim/configs/_base_/datasets/ffhq_flip.py
mmagic/.mim/configs/_base_/datasets/grow_scale_imgs_ffhq_styleganv1.py
mmagic/.mim/configs/_base_/datasets/imagenet_128.py
mmagic/.mim/configs/_base_/datasets/imagenet_256.py
mmagic/.mim/configs/_base_/datasets/imagenet_512.py
mmagic/.mim/configs/_base_/datasets/imagenet_64.py
mmagic/.mim/configs/_base_/datasets/imagenet_noaug_128.py
mmagic/.mim/configs/_base_/datasets/liif_test_config.py
mmagic/.mim/configs/_base_/datasets/lsun_stylegan.py
mmagic/.mim/configs/_base_/datasets/paired_imgs_256x256_crop.py
mmagic/.mim/configs/_base_/datasets/places.py
mmagic/.mim/configs/_base_/datasets/sisr_x2_test_config.py
mmagic/.mim/configs/_base_/datasets/sisr_x3_test_config.py
mmagic/.mim/configs/_base_/datasets/sisr_x4_test_config.py
mmagic/.mim/configs/_base_/datasets/tdan_test_config.py
mmagic/.mim/configs/_base_/datasets/unconditional_imgs_128x128.py
mmagic/.mim/configs/_base_/datasets/unconditional_imgs_64x64.py
mmagic-1.2.0.dist-info/LICENSE
mmagic-1.2.0.dist-info/METADATA
mmagic-1.2.0.dist-info/WHEEL
mmagic-1.2.0.dist-info/top_level.txt
mmagic-1.2.0.dist-info/RECORD
