Metadata-Version: 2.1
Name: mmagic
Version: 1.2.0
Summary: OpenMMLab Multimodal Advanced, Generative, and Intelligent Creation Toolbox
Home-page: https://github.com/open-mmlab/mmagic
Maintainer: MMagic Contributors
Maintainer-email: openmmlab@gmail.com
License: Apache License 2.0
Keywords: computer vision,super resolution,video interpolation,inpainting,matting,SISR,RefSR,VSR,GAN,VFI
Platform: UNKNOWN
Classifier: Development Status :: 4 - Beta
Classifier: Intended Audience :: Developers
Classifier: Intended Audience :: Education
Classifier: Intended Audience :: Science/Research
Classifier: License :: OSI Approved :: Apache Software License
Classifier: Operating System :: OS Independent
Classifier: Programming Language :: Python :: 3
Classifier: Programming Language :: Python :: 3.7
Classifier: Programming Language :: Python :: 3.8
Classifier: Programming Language :: Python :: 3.9
Classifier: Programming Language :: Python :: 3.10
Classifier: Topic :: Scientific/Engineering :: Artificial Intelligence
Classifier: Topic :: Scientific/Engineering :: Image Processing
Requires-Dist: av
Requires-Dist: click
Requires-Dist: controlnet-aux
Requires-Dist: diffusers >=0.23.0
Requires-Dist: einops
Requires-Dist: face-alignment <=1.3.4
Requires-Dist: facexlib
Requires-Dist: lmdb
Requires-Dist: lpips
Requires-Dist: mediapipe
Requires-Dist: numpy
Requires-Dist: opencv-python !=4.5.5.62,!=4.5.5.64
Requires-Dist: pandas
Requires-Dist: Pillow
Requires-Dist: resize-right
Requires-Dist: tensorboard
Requires-Dist: transformers >=4.27.4
Requires-Dist: av ==8.0.3 ; python_version < "3.7"
Provides-Extra: all
Requires-Dist: av ; extra == 'all'
Requires-Dist: click ; extra == 'all'
Requires-Dist: controlnet-aux ; extra == 'all'
Requires-Dist: diffusers >=0.23.0 ; extra == 'all'
Requires-Dist: einops ; extra == 'all'
Requires-Dist: face-alignment <=1.3.4 ; extra == 'all'
Requires-Dist: facexlib ; extra == 'all'
Requires-Dist: lmdb ; extra == 'all'
Requires-Dist: lpips ; extra == 'all'
Requires-Dist: mediapipe ; extra == 'all'
Requires-Dist: numpy ; extra == 'all'
Requires-Dist: opencv-python !=4.5.5.62,!=4.5.5.64 ; extra == 'all'
Requires-Dist: pandas ; extra == 'all'
Requires-Dist: Pillow ; extra == 'all'
Requires-Dist: resize-right ; extra == 'all'
Requires-Dist: tensorboard ; extra == 'all'
Requires-Dist: transformers >=4.27.4 ; extra == 'all'
Requires-Dist: albumentations ; extra == 'all'
Requires-Dist: clip ; extra == 'all'
Requires-Dist: coverage <7.0.0 ; extra == 'all'
Requires-Dist: imageio-ffmpeg ==0.4.4 ; extra == 'all'
Requires-Dist: interrogate ; extra == 'all'
Requires-Dist: mmdet >=3.0.0 ; extra == 'all'
Requires-Dist: pytest ; extra == 'all'
Requires-Dist: open-clip-torch ; extra == 'all'
Requires-Dist: PyQt5 ; extra == 'all'
Requires-Dist: av ==8.0.3 ; (python_version < "3.7") and extra == 'all'
Provides-Extra: mim
Requires-Dist: mmcv >=2.0.0 ; extra == 'mim'
Requires-Dist: mmengine >=0.4.0 ; extra == 'mim'
Provides-Extra: tests
Requires-Dist: albumentations ; extra == 'tests'
Requires-Dist: clip ; extra == 'tests'
Requires-Dist: controlnet-aux ; extra == 'tests'
Requires-Dist: coverage <7.0.0 ; extra == 'tests'
Requires-Dist: imageio-ffmpeg ==0.4.4 ; extra == 'tests'
Requires-Dist: interrogate ; extra == 'tests'
Requires-Dist: mmdet >=3.0.0 ; extra == 'tests'
Requires-Dist: pytest ; extra == 'tests'
Requires-Dist: transformers >=4.27.4 ; extra == 'tests'
